dumped/__init__.py
dumped/mutables.py
dumped-0.2.5.dist-info/DESCRIPTION.rst
dumped-0.2.5.dist-info/METADATA
dumped-0.2.5.dist-info/RECORD
dumped-0.2.5.dist-info/WHEEL
dumped-0.2.5.dist-info/metadata.json
dumped-0.2.5.dist-info/top_level.txt
