Metadata-Version: 2.0
Name: dumped
Version: 0.2.5
Summary: Easy & lightweight objects persistence
Home-page: https://github.com/GoldsteinE/dumped
Author: GoldsteinE
Author-email: mouse-art@ya.ru
License: MIT
Download-URL: https://github.com/GoldsteinE/dumped/archive/0.2.5.tar.gz
Keywords: dumping json persistence lightweight
Platform: UNKNOWN
Classifier: Programming Language :: Python :: 3
Classifier: Programming Language :: Python :: 3.3
Classifier: Programming Language :: Python :: 3.4
Classifier: Programming Language :: Python :: 3.5
Classifier: Programming Language :: Python :: 3.6
Classifier: License :: OSI Approved :: MIT License
